sksurgeryoverlay/__init__.py
sksurgeryoverlay/_version.py
sksurgeryoverlay/utils/__init__.py
sksurgeryoverlay/utils/platform_utils.py
sksurgeryoverlay/vtk/QVTKRenderWindowInteractor.py
sksurgeryoverlay/vtk/__init__.py
sksurgeryoverlay/vtk/vtk_base_model.py
sksurgeryoverlay/vtk/vtk_overlay_window.py
sksurgeryoverlay/vtk/vtk_point_model.py
sksurgeryoverlay/vtk/vtk_surface_model.py
sksurgeryoverlay/vtk/vtk_surface_model_directory_loader.py
tests/vtk/__init__.py
tests/vtk/conftest.py
tests/vtk/test_vtk_overlay_window.py
tests/vtk/test_vtk_point_model.py
tests/vtk/test_vtk_surface_model.py
tests/vtk/test_vtk_surface_model_directory_loader.py
scikit_surgeryoverlay-0.1.3.dist-info/LICENSE
scikit_surgeryoverlay-0.1.3.dist-info/METADATA
scikit_surgeryoverlay-0.1.3.dist-info/WHEEL
scikit_surgeryoverlay-0.1.3.dist-info/entry_points.txt
scikit_surgeryoverlay-0.1.3.dist-info/top_level.txt
scikit_surgeryoverlay-0.1.3.dist-info/RECORD
