Metadata-Version: 2.1
Name: scikit-surgeryoverlay
Version: 0.1.3
Summary: scikit-surgeryoverlay
Home-page: https://weisslab.cs.ucl.ac.uk/WEISS/SoftwareRepositories/SNAPPY/scikit-surgeryoverlay
Author: Thomas Dowrick
Author-email: t.dowrick@ucl.ac.uk
License: BSD-3 license
Keywords: medical imaging
Platform: UNKNOWN
Classifier: Development Status :: 3 - Alpha
Classifier: Intended Audience :: Developers
Classifier: Intended Audience :: Healthcare Industry
Classifier: Intended Audience :: Information Technology
Classifier: Intended Audience :: Science/Research
Classifier: License :: OSI Approved :: BSD License
Classifier: Programming Language :: Python
Classifier: Programming Language :: Python :: 2
Classifier: Programming Language :: Python :: 3
Classifier: Topic :: Scientific/Engineering :: Information Analysis
Classifier: Topic :: Scientific/Engineering :: Medical Science Apps.
Requires-Dist: six (>=1.10)
Requires-Dist: numpy (>=1.11)
Requires-Dist: vtk (>=8.1.2)
Requires-Dist: PySide2 (>=5.12.0)
Requires-Dist: scikit-surgerycore (>=0.1.1)
